{
  "id": "docs",
  "name": "Documentation",
  "url": "https://tensamin.methanium.net/docs/",
  "checks": [
    {
      "t": "2025-10-07T13:07:57.001Z",
      "ok": true,
      "code": 200,
      "rt": 106
    },
    {
      "t": "2025-10-07T13:38:49.476Z",
      "ok": true,
      "code": 200,
      "rt": 105
    },
    {
      "t": "2025-10-07T13:51:14.121Z",
      "ok": true,
      "code": 200,
      "rt": 101
    },
    {
      "t": "2025-10-07T14:10:38.078Z",
      "ok": true,
      "code": 200,
      "rt": 149
    },
    {
      "t": "2025-10-07T14:35:03.552Z",
      "ok": true,
      "code": 200,
      "rt": 129
    },
    {
      "t": "2025-10-07T14:49:43.873Z",
      "ok": true,
      "code": 200,
      "rt": 101
    },
    {
      "t": "2025-10-07T14:59:53.015Z",
      "ok": true,
      "code": 200,
      "rt": 144
    },
    {
      "t": "2025-10-07T15:28:40.020Z",
      "ok": true,
      "code": 200,
      "rt": 123
    },
    {
      "t": "2025-10-07T15:43:59.820Z",
      "ok": true,
      "code": 200,
      "rt": 104
    },
    {
      "t": "2025-10-07T15:54:45.156Z",
      "ok": true,
      "code": 200,
      "rt": 176
    },
    {
      "t": "2025-10-07T16:20:55.610Z",
      "ok": true,
      "code": 200,
      "rt": 121
    },
    {
      "t": "2025-10-07T16:42:45.659Z",
      "ok": true,
      "code": 200,
      "rt": 129
    },
    {
      "t": "2025-10-07T16:54:41.969Z",
      "ok": true,
      "code": 200,
      "rt": 105
    },
    {
      "t": "2025-10-07T17:15:11.160Z",
      "ok": true,
      "code": 200,
      "rt": 103
    },
    {
      "t": "2025-10-07T17:32:30.889Z",
      "ok": true,
      "code": 200,
      "rt": 173
    },
    {
      "t": "2025-10-07T17:43:34.368Z",
      "ok": true,
      "code": 200,
      "rt": 146
    },
    {
      "t": "2025-10-07T17:53:47.937Z",
      "ok": true,
      "code": 200,
      "rt": 174
    },
    {
      "t": "2025-10-07T18:22:05.459Z",
      "ok": true,
      "code": 200,
      "rt": 101
    },
    {
      "t": "2025-10-07T18:46:15.131Z",
      "ok": true,
      "code": 200,
      "rt": 124
    },
    {
      "t": "2025-10-07T18:56:11.016Z",
      "ok": true,
      "code": 200,
      "rt": 106
    },
    {
      "t": "2025-10-07T19:16:09.359Z",
      "ok": true,
      "code": 200,
      "rt": 101
    },
    {
      "t": "2025-10-07T19:27:02.612Z",
      "ok": true,
      "code": 200,
      "rt": 121
    },
    {
      "t": "2025-10-07T19:39:00.171Z",
      "ok": true,
      "code": 200,
      "rt": 106
    },
    {
      "t": "2025-10-07T19:49:33.127Z",
      "ok": true,
      "code": 200,
      "rt": 136
    },
    {
      "t": "2025-10-07T19:59:37.565Z",
      "ok": true,
      "code": 200,
      "rt": 173
    },
    {
      "t": "2025-10-07T20:27:46.702Z",
      "ok": true,
      "code": 200,
      "rt": 104
    },
    {
      "t": "2025-10-07T20:41:56.983Z",
      "ok": true,
      "code": 200,
      "rt": 173
    },
    {
      "t": "2025-10-07T20:52:23.667Z",
      "ok": true,
      "code": 200,
      "rt": 101
    },
    {
      "t": "2025-10-07T21:10:30.895Z",
      "ok": true,
      "code": 200,
      "rt": 177
    },
    {
      "t": "2025-10-07T21:26:58.763Z",
      "ok": true,
      "code": 200,
      "rt": 105
    },
    {
      "t": "2025-10-07T21:38:24.877Z",
      "ok": true,
      "code": 200,
      "rt": 176
    },
    {
      "t": "2025-10-07T21:48:53.639Z",
      "ok": true,
      "code": 200,
      "rt": 161
    },
    {
      "t": "2025-10-07T21:58:54.423Z",
      "ok": true,
      "code": 200,
      "rt": 119
    },
    {
      "t": "2025-10-07T22:24:08.338Z",
      "ok": true,
      "code": 200,
      "rt": 170
    },
    {
      "t": "2025-10-07T22:37:23.131Z",
      "ok": true,
      "code": 200,
      "rt": 119
    },
    {
      "t": "2025-10-07T22:47:21.038Z",
      "ok": true,
      "code": 200,
      "rt": 104
    },
    {
      "t": "2025-10-07T22:57:22.398Z",
      "ok": true,
      "code": 200,
      "rt": 105
    },
    {
      "t": "2025-10-07T23:20:10.984Z",
      "ok": true,
      "code": 200,
      "rt": 118
    },
    {
      "t": "2025-10-07T23:30:25.834Z",
      "ok": true,
      "code": 200,
      "rt": 119
    },
    {
      "t": "2025-10-07T23:40:11.742Z",
      "ok": true,
      "code": 200,
      "rt": 101
    },
    {
      "t": "2025-10-07T23:50:35.007Z",
      "ok": true,
      "code": 200,
      "rt": 104
    },
    {
      "t": "2025-10-08T00:37:43.232Z",
      "ok": true,
      "code": 200,
      "rt": 121
    },
    {
      "t": "2025-10-08T02:10:56.530Z",
      "ok": true,
      "code": 200,
      "rt": 138
    },
    {
      "t": "2025-10-08T03:05:52.038Z",
      "ok": true,
      "code": 200,
      "rt": 174
    },
    {
      "t": "2025-10-08T03:37:22.460Z",
      "ok": true,
      "code": 200,
      "rt": 175
    },
    {
      "t": "2025-10-08T03:51:14.781Z",
      "ok": true,
      "code": 200,
      "rt": 119
    },
    {
      "t": "2025-10-08T04:11:48.936Z",
      "ok": true,
      "code": 200,
      "rt": 124
    },
    {
      "t": "2025-10-08T04:34:19.999Z",
      "ok": true,
      "code": 200,
      "rt": 106
    },
    {
      "t": "2025-10-08T04:46:51.400Z",
      "ok": true,
      "code": 200,
      "rt": 109
    },
    {
      "t": "2025-10-08T04:57:24.563Z",
      "ok": true,
      "code": 200,
      "rt": 121
    },
    {
      "t": "2025-10-08T05:22:28.312Z",
      "ok": true,
      "code": 200,
      "rt": 126
    },
    {
      "t": "2025-10-08T05:38:31.481Z",
      "ok": true,
      "code": 200,
      "rt": 111
    },
    {
      "t": "2025-10-08T05:48:34.098Z",
      "ok": true,
      "code": 200,
      "rt": 103
    },
    {
      "t": "2025-10-08T05:58:58.652Z",
      "ok": true,
      "code": 200,
      "rt": 150
    },
    {
      "t": "2025-10-08T06:38:12.084Z",
      "ok": true,
      "code": 200,
      "rt": 151
    },
    {
      "t": "2025-10-08T06:53:08.751Z",
      "ok": true,
      "code": 200,
      "rt": 121
    },
    {
      "t": "2025-10-08T07:13:43.246Z",
      "ok": true,
      "code": 200,
      "rt": 162
    },
    {
      "t": "2025-10-08T07:30:07.988Z",
      "ok": true,
      "code": 200,
      "rt": 110
    },
    {
      "t": "2025-10-08T07:42:03.057Z",
      "ok": true,
      "code": 200,
      "rt": 137
    },
    {
      "t": "2025-10-08T07:52:29.151Z",
      "ok": true,
      "code": 200,
      "rt": 164
    },
    {
      "t": "2025-10-08T08:17:32.183Z",
      "ok": true,
      "code": 200,
      "rt": 144
    },
    {
      "t": "2025-10-08T08:41:59.923Z",
      "ok": true,
      "code": 200,
      "rt": 134
    },
    {
      "t": "2025-10-08T08:55:18.100Z",
      "ok": true,
      "code": 200,
      "rt": 174
    },
    {
      "t": "2025-10-08T09:19:40.233Z",
      "ok": true,
      "code": 200,
      "rt": 135
    },
    {
      "t": "2025-10-08T09:37:24.952Z",
      "ok": true,
      "code": 200,
      "rt": 181
    },
    {
      "t": "2025-10-08T09:48:01.207Z",
      "ok": true,
      "code": 200,
      "rt": 181
    },
    {
      "t": "2025-10-08T09:57:54.533Z",
      "ok": true,
      "code": 200,
      "rt": 110
    },
    {
      "t": "2025-10-08T10:25:36.663Z",
      "ok": true,
      "code": 200,
      "rt": 106
    },
    {
      "t": "2025-10-08T10:42:42.005Z",
      "ok": true,
      "code": 200,
      "rt": 151
    },
    {
      "t": "2025-10-08T10:52:40.211Z",
      "ok": true,
      "code": 200,
      "rt": 119
    },
    {
      "t": "2025-10-08T11:10:41.334Z",
      "ok": true,
      "code": 200,
      "rt": 109
    },
    {
      "t": "2025-10-08T11:26:15.681Z",
      "ok": true,
      "code": 200,
      "rt": 103
    },
    {
      "t": "2025-10-08T11:38:23.110Z",
      "ok": true,
      "code": 200,
      "rt": 123
    },
    {
      "t": "2025-10-08T11:48:49.613Z",
      "ok": true,
      "code": 200,
      "rt": 108
    },
    {
      "t": "2025-10-08T11:58:59.770Z",
      "ok": true,
      "code": 200,
      "rt": 103
    },
    {
      "t": "2025-10-08T12:54:51.474Z",
      "ok": true,
      "code": 200,
      "rt": 182
    },
    {
      "t": "2025-10-08T13:27:54.334Z",
      "ok": true,
      "code": 200,
      "rt": 104
    },
    {
      "t": "2025-10-08T13:46:32.084Z",
      "ok": true,
      "code": 200,
      "rt": 111
    },
    {
      "t": "2025-10-08T13:57:05.206Z",
      "ok": true,
      "code": 200,
      "rt": 174
    },
    {
      "t": "2025-10-08T14:23:13.753Z",
      "ok": true,
      "code": 200,
      "rt": 130
    },
    {
      "t": "2025-10-08T14:42:31.180Z",
      "ok": true,
      "code": 200,
      "rt": 105
    },
    {
      "t": "2025-10-08T14:52:43.019Z",
      "ok": true,
      "code": 200,
      "rt": 109
    },
    {
      "t": "2025-10-08T15:13:51.641Z",
      "ok": true,
      "code": 200,
      "rt": 163
    },
    {
      "t": "2025-10-08T15:34:06.871Z",
      "ok": true,
      "code": 200,
      "rt": 128
    },
    {
      "t": "2025-10-08T15:46:43.211Z",
      "ok": true,
      "code": 200,
      "rt": 109
    },
    {
      "t": "2025-10-08T15:57:19.676Z",
      "ok": true,
      "code": 200,
      "rt": 182
    },
    {
      "t": "2025-10-08T16:28:51.532Z",
      "ok": true,
      "code": 200,
      "rt": 109
    },
    {
      "t": "2025-10-08T16:47:41.591Z",
      "ok": true,
      "code": 200,
      "rt": 110
    },
    {
      "t": "2025-10-08T16:58:05.191Z",
      "ok": true,
      "code": 200,
      "rt": 164
    },
    {
      "t": "2025-10-08T17:21:49.310Z",
      "ok": true,
      "code": 200,
      "rt": 125
    },
    {
      "t": "2025-10-08T17:37:24.756Z",
      "ok": true,
      "code": 200,
      "rt": 105
    },
    {
      "t": "2025-10-08T17:47:40.915Z",
      "ok": true,
      "code": 200,
      "rt": 123
    },
    {
      "t": "2025-10-08T17:57:42.689Z",
      "ok": true,
      "code": 200,
      "rt": 142
    },
    {
      "t": "2025-10-08T18:35:13.383Z",
      "ok": true,
      "code": 200,
      "rt": 123
    },
    {
      "t": "2025-10-08T18:52:53.269Z",
      "ok": true,
      "code": 200,
      "rt": 127
    },
    {
      "t": "2025-10-08T19:10:20.483Z",
      "ok": true,
      "code": 200,
      "rt": 176
    },
    {
      "t": "2025-10-08T19:24:51.438Z",
      "ok": true,
      "code": 200,
      "rt": 109
    },
    {
      "t": "2025-10-08T19:36:46.350Z",
      "ok": true,
      "code": 200,
      "rt": 108
    },
    {
      "t": "2025-10-08T19:47:11.072Z",
      "ok": true,
      "code": 200,
      "rt": 121
    },
    {
      "t": "2025-10-08T19:57:09.856Z",
      "ok": true,
      "code": 200,
      "rt": 109
    },
    {
      "t": "2025-10-08T20:24:58.558Z",
      "ok": true,
      "code": 200,
      "rt": 150
    },
    {
      "t": "2025-10-08T20:39:29.646Z",
      "ok": true,
      "code": 200,
      "rt": 106
    },
    {
      "t": "2025-10-08T20:49:41.465Z",
      "ok": true,
      "code": 200,
      "rt": 103
    },
    {
      "t": "2025-10-08T20:59:41.759Z",
      "ok": true,
      "code": 200,
      "rt": 161
    },
    {
      "t": "2025-10-08T21:23:12.808Z",
      "ok": true,
      "code": 200,
      "rt": 125
    },
    {
      "t": "2025-10-08T21:34:25.113Z",
      "ok": true,
      "code": 200,
      "rt": 122
    },
    {
      "t": "2025-10-08T21:44:50.245Z",
      "ok": true,
      "code": 200,
      "rt": 111
    },
    {
      "t": "2025-10-08T21:54:58.705Z",
      "ok": true,
      "code": 200,
      "rt": 110
    },
    {
      "t": "2025-10-08T22:16:16.020Z",
      "ok": true,
      "code": 200,
      "rt": 174
    },
    {
      "t": "2025-10-08T22:34:16.647Z",
      "ok": true,
      "code": 200,
      "rt": 106
    },
    {
      "t": "2025-10-08T22:44:15.861Z",
      "ok": true,
      "code": 200,
      "rt": 107
    },
    {
      "t": "2025-10-08T22:54:30.427Z",
      "ok": true,
      "code": 200,
      "rt": 111
    },
    {
      "t": "2025-10-08T23:14:46.826Z",
      "ok": true,
      "code": 200,
      "rt": 167
    },
    {
      "t": "2025-10-08T23:29:16.009Z",
      "ok": true,
      "code": 200,
      "rt": 106
    },
    {
      "t": "2025-10-08T23:40:50.236Z",
      "ok": true,
      "code": 200,
      "rt": 110
    },
    {
      "t": "2025-10-08T23:51:05.905Z",
      "ok": true,
      "code": 200,
      "rt": 173
    },
    {
      "t": "2025-10-09T00:42:12.825Z",
      "ok": true,
      "code": 200,
      "rt": 179
    },
    {
      "t": "2025-10-09T02:13:40.843Z",
      "ok": true,
      "code": 200,
      "rt": 121
    },
    {
      "t": "2025-10-09T03:09:35.091Z",
      "ok": true,
      "code": 200,
      "rt": 164
    },
    {
      "t": "2025-10-09T03:42:21.261Z",
      "ok": true,
      "code": 200,
      "rt": 168
    },
    {
      "t": "2025-10-09T03:54:12.629Z",
      "ok": true,
      "code": 200,
      "rt": 121
    },
    {
      "t": "2025-10-09T04:19:12.932Z",
      "ok": true,
      "code": 200,
      "rt": 109
    },
    {
      "t": "2025-10-09T04:39:03.488Z",
      "ok": true,
      "code": 200,
      "rt": 180
    },
    {
      "t": "2025-10-09T04:50:33.626Z",
      "ok": true,
      "code": 200,
      "rt": 109
    },
    {
      "t": "2025-10-09T05:01:23.270Z",
      "ok": true,
      "code": 200,
      "rt": 172
    },
    {
      "t": "2025-10-09T05:27:40.838Z",
      "ok": true,
      "code": 200,
      "rt": 129
    },
    {
      "t": "2025-10-09T05:42:07.948Z",
      "ok": true,
      "code": 200,
      "rt": 126
    },
    {
      "t": "2025-10-09T05:52:30.157Z",
      "ok": true,
      "code": 200,
      "rt": 109
    },
    {
      "t": "2025-10-09T06:19:39.301Z",
      "ok": true,
      "code": 200,
      "rt": 121
    },
    {
      "t": "2025-10-09T06:46:56.673Z",
      "ok": true,
      "code": 200,
      "rt": 126
    },
    {
      "t": "2025-10-09T06:57:33.939Z",
      "ok": true,
      "code": 200,
      "rt": 126
    },
    {
      "t": "2025-10-09T07:22:25.980Z",
      "ok": true,
      "code": 200,
      "rt": 106
    },
    {
      "t": "2025-10-09T07:35:50.058Z",
      "ok": true,
      "code": 200,
      "rt": 126
    },
    {
      "t": "2025-10-09T07:46:06.813Z",
      "ok": true,
      "code": 200,
      "rt": 110
    },
    {
      "t": "2025-10-09T07:55:46.191Z",
      "ok": true,
      "code": 200,
      "rt": 121
    },
    {
      "t": "2025-10-09T08:27:02.551Z",
      "ok": true,
      "code": 200,
      "rt": 105
    },
    {
      "t": "2025-10-09T08:47:57.895Z",
      "ok": true,
      "code": 200,
      "rt": 181
    },
    {
      "t": "2025-10-09T08:58:27.248Z",
      "ok": true,
      "code": 200,
      "rt": 111
    },
    {
      "t": "2025-10-09T09:27:24.282Z",
      "ok": true,
      "code": 200,
      "rt": 143
    },
    {
      "t": "2025-10-09T09:42:05.536Z",
      "ok": true,
      "code": 200,
      "rt": 151
    },
    {
      "t": "2025-10-09T09:52:11.995Z",
      "ok": true,
      "code": 200,
      "rt": 183
    },
    {
      "t": "2025-10-09T10:13:05.437Z",
      "ok": true,
      "code": 200,
      "rt": 160
    },
    {
      "t": "2025-10-09T10:37:29.574Z",
      "ok": true,
      "code": 200,
      "rt": 182
    },
    {
      "t": "2025-10-09T10:49:26.887Z",
      "ok": true,
      "code": 200,
      "rt": 126
    },
    {
      "t": "2025-10-09T10:59:37.652Z",
      "ok": true,
      "code": 200,
      "rt": 105
    },
    {
      "t": "2025-10-09T11:22:18.921Z",
      "ok": true,
      "code": 200,
      "rt": 175
    },
    {
      "t": "2025-10-09T11:34:38.513Z",
      "ok": true,
      "code": 200,
      "rt": 122
    },
    {
      "t": "2025-10-09T11:44:42.138Z",
      "ok": true,
      "code": 200,
      "rt": 168
    },
    {
      "t": "2025-10-09T11:55:07.571Z",
      "ok": true,
      "code": 200,
      "rt": 182
    },
    {
      "t": "2025-10-09T12:37:48.686Z",
      "ok": true,
      "code": 200,
      "rt": 165
    },
    {
      "t": "2025-10-09T13:17:37.744Z",
      "ok": true,
      "code": 200,
      "rt": 122
    },
    {
      "t": "2025-10-09T13:54:45.934Z",
      "ok": true,
      "code": 200,
      "rt": 143
    },
    {
      "t": "2025-10-09T14:17:38.038Z",
      "ok": true,
      "code": 200,
      "rt": 106
    },
    {
      "t": "2025-10-09T14:47:39.265Z",
      "ok": true,
      "code": 200,
      "rt": 181
    },
    {
      "t": "2025-10-09T15:18:50.895Z",
      "ok": true,
      "code": 200,
      "rt": 150
    },
    {
      "t": "2025-10-09T15:23:26.829Z",
      "ok": true,
      "code": 200,
      "rt": 181
    },
    {
      "t": "2025-10-09T15:37:22.814Z",
      "ok": true,
      "code": 200,
      "rt": 103
    },
    {
      "t": "2025-10-09T15:54:25.848Z",
      "ok": true,
      "code": 200,
      "rt": 182
    },
    {
      "t": "2025-10-09T16:21:23.611Z",
      "ok": true,
      "code": 200,
      "rt": 119
    },
    {
      "t": "2025-10-09T16:45:10.410Z",
      "ok": true,
      "code": 200,
      "rt": 107
    },
    {
      "t": "2025-10-09T16:58:23.889Z",
      "ok": true,
      "code": 200,
      "rt": 146
    },
    {
      "t": "2025-10-09T17:23:39.910Z",
      "ok": true,
      "code": 200,
      "rt": 165
    },
    {
      "t": "2025-10-09T17:39:02.009Z",
      "ok": true,
      "code": 200,
      "rt": 124
    },
    {
      "t": "2025-10-09T17:49:46.981Z",
      "ok": true,
      "code": 200,
      "rt": 123
    },
    {
      "t": "2025-10-09T17:59:39.091Z",
      "ok": true,
      "code": 200,
      "rt": 180
    },
    {
      "t": "2025-10-09T18:36:35.444Z",
      "ok": true,
      "code": 200,
      "rt": 181
    },
    {
      "t": "2025-10-09T18:52:12.678Z",
      "ok": true,
      "code": 200,
      "rt": 141
    },
    {
      "t": "2025-10-09T19:09:48.603Z",
      "ok": true,
      "code": 200,
      "rt": 174
    },
    {
      "t": "2025-10-09T19:25:07.140Z",
      "ok": true,
      "code": 200,
      "rt": 105
    },
    {
      "t": "2025-10-09T19:36:54.254Z",
      "ok": true,
      "code": 200,
      "rt": 110
    },
    {
      "t": "2025-10-09T19:47:05.233Z",
      "ok": true,
      "code": 200,
      "rt": 109
    },
    {
      "t": "2025-10-09T19:57:15.551Z",
      "ok": true,
      "code": 200,
      "rt": 140
    },
    {
      "t": "2025-10-09T20:25:41.459Z",
      "ok": true,
      "code": 200,
      "rt": 110
    },
    {
      "t": "2025-10-09T20:40:40.994Z",
      "ok": true,
      "code": 200,
      "rt": 130
    },
    {
      "t": "2025-10-09T20:51:14.100Z",
      "ok": true,
      "code": 200,
      "rt": 109
    },
    {
      "t": "2025-10-09T21:08:59.648Z",
      "ok": true,
      "code": 200,
      "rt": 109
    },
    {
      "t": "2025-10-09T21:26:51.231Z",
      "ok": true,
      "code": 200,
      "rt": 108
    },
    {
      "t": "2025-10-09T21:38:48.951Z",
      "ok": true,
      "code": 200,
      "rt": 119
    },
    {
      "t": "2025-10-09T21:48:57.769Z",
      "ok": true,
      "code": 200,
      "rt": 143
    },
    {
      "t": "2025-10-09T21:58:52.601Z",
      "ok": true,
      "code": 200,
      "rt": 164
    },
    {
      "t": "2025-10-09T22:24:08.678Z",
      "ok": true,
      "code": 200,
      "rt": 129
    },
    {
      "t": "2025-10-09T22:37:50.264Z",
      "ok": true,
      "code": 200,
      "rt": 107
    },
    {
      "t": "2025-10-09T22:48:11.053Z",
      "ok": true,
      "code": 200,
      "rt": 116
    },
    {
      "t": "2025-10-09T22:58:13.043Z",
      "ok": true,
      "code": 200,
      "rt": 127
    },
    {
      "t": "2025-10-09T23:21:58.804Z",
      "ok": true,
      "code": 200,
      "rt": 171
    },
    {
      "t": "2025-10-09T23:32:39.970Z",
      "ok": true,
      "code": 200,
      "rt": 152
    },
    {
      "t": "2025-10-09T23:43:05.135Z",
      "ok": true,
      "code": 200,
      "rt": 173
    },
    {
      "t": "2025-10-09T23:53:33.450Z",
      "ok": true,
      "code": 200,
      "rt": 111
    },
    {
      "t": "2025-10-10T01:06:39.500Z",
      "ok": true,
      "code": 200,
      "rt": 136
    },
    {
      "t": "2025-10-10T02:38:45.659Z",
      "ok": true,
      "code": 200,
      "rt": 121
    },
    {
      "t": "2025-10-10T03:23:07.570Z",
      "ok": true,
      "code": 200,
      "rt": 180
    },
    {
      "t": "2025-10-10T03:46:17.012Z",
      "ok": true,
      "code": 200,
      "rt": 175
    },
    {
      "t": "2025-10-10T03:56:44.114Z",
      "ok": true,
      "code": 200,
      "rt": 180
    },
    {
      "t": "2025-10-10T04:25:47.575Z",
      "ok": true,
      "code": 200,
      "rt": 160
    },
    {
      "t": "2025-10-10T04:42:38.850Z",
      "ok": true,
      "code": 200,
      "rt": 104
    },
    {
      "t": "2025-10-10T04:52:45.280Z",
      "ok": true,
      "code": 200,
      "rt": 167
    },
    {
      "t": "2025-10-10T05:12:53.802Z",
      "ok": true,
      "code": 200,
      "rt": 107
    },
    {
      "t": "2025-10-10T05:32:59.576Z",
      "ok": true,
      "code": 200,
      "rt": 130
    },
    {
      "t": "2025-10-10T05:44:31.671Z",
      "ok": true,
      "code": 200,
      "rt": 125
    },
    {
      "t": "2025-10-10T05:55:06.324Z",
      "ok": true,
      "code": 200,
      "rt": 151
    },
    {
      "t": "2025-10-10T06:27:38.273Z",
      "ok": true,
      "code": 200,
      "rt": 124
    },
    {
      "t": "2025-10-10T06:50:31.524Z",
      "ok": true,
      "code": 200,
      "rt": 125
    }
  ]
}